Workbook

Sheet 1_Параметры
A1: ДЗ-17 · Sizing и стоимость инференса Llama-3-70B · 1000 RPM
A2: Жёлтые ячейки — входные параметры (можно менять), зелёные — расчёт по формулам.
A4: МОДЕЛЬ (Llama-3-70B)
A5: Число параметров, млрд (N) | B5: 70.6 | C5: Meta Llama-3-70B(-Instruct)
A6: Слоёв (L) | B6: 80 | C6: конфиг модели
A7: KV-голов (GQA) | B7: 8 | C7: grouped-query attention
A8: Размерность головы (head_dim) | B8: 128
A9: Байт/параметр FP16 | B9: 2 | C9: формула лекции: точность
A10: Байт/параметр INT4 (эффективно) | B10: 0.55 | C10: 0.5 + ~10% на scales/zero-points (AWQ/GPTQ)
A11: Байт/элемент KV-кэша | B11: 2 | C11: KV консервативно в FP16 в обоих сценариях
A12: НАГРУЗКА
A13: RPM (запросов в минуту) | B13: 1000 | C13: условие задачи
A14: RPS | B14: =B13/60
A15: Токенов на входе (prompt), ср. | B15: 800 | C15: допущение: чат с контекстом
A16: Токенов на выходе (generation), ср. | B16: 250 | C16: допущение
A17: Требуемый суммарный decode, ток/с | B17: =B14*B16 | C17: RPS × выходные токены
A18: МОДЕЛЬ ОБСЛУЖИВАНИЯ (оценки)
A19: Скорость декодинга FP16, ток/с на запрос | B19: 30 | C19: TP=4 A100, эфф. утилизация ~50%
A20: Скорость декодинга INT4, ток/с на запрос | B20: 40 | C20: TP=2 A100, memory-bound выигрыш
A21: Prefill, с (условно) | B21: 1 | C21: обработка входного контекста
A22: Overhead VRAM (CUDA, активации, буферы), % | B22: 10 | C22: формула лекции: + Overhead
A23: Часов в месяце | B23: 730

Sheet 2_Sizing_VRAM
A1: Шаг 1 · Hardware Sizing: VRAM = Параметры × Точность + KV-кэш + Overhead
A3: Величина | B3: FP16 | C3: INT4 | D3: Формула / комментарий
A4: Веса модели, ГБ | B4: ='1_Параметры'!B5*'1_Параметры'!B9 | C4: ='1_Параметры'!B5*'1_Параметры'!B10 | D4: N млрд × байт/параметр
A5: KV-кэш на 1 токен, МБ | B5: =2*'1_Параметры'!B6*'1_Параметры'!B7*'1_Параметры'!B8*'1_Параметры'!B11/1000000 | C5: =2*'1_Параметры'!B6*'1_Параметры'!B7*'1_Параметры'!B8*'1_Параметры'!B11/1000000 | D5: 2(K и V) × L × kv_heads × head_dim × байт (GQA!)
A6: Время обслуживания запроса, с | B6: ='1_Параметры'!B16/'1_Параметры'!B19+'1_Параметры'!B21 | C6: ='1_Параметры'!B16/'1_Параметры'!B20+'1_Параметры'!B21 | D6: decode + prefill
A7: Одновременных запросов (Little's law) | B7: ='1_Параметры'!B14*B6 | C7: ='1_Параметры'!B14*C6 | D7: RPS × время обслуживания
A8: Средний контекст живого запроса, токенов | B8: ='1_Параметры'!B15+'1_Параметры'!B16/2 | C8: ='1_Параметры'!B15+'1_Параметры'!B16/2 | D8: вход + половина выхода
A9: KV-кэш суммарно, ГБ | B9: =B7*B8*B5/1000 | C9: =C7*C8*C5/1000 | D9: конкурентность × контекст × КВ/токен
A10: ИТОГО VRAM, ГБ | B10: =(B4+B9)*(1+'1_Параметры'!B22/100) | C10: =(C4+C9)*(1+'1_Параметры'!B22/100) | D10: (веса + KV) × (1 + Overhead)
A12: Сколько и каких GPU нужно по памяти (шт., ceil(VRAM/объём); скобки — выравнивание под tensor parallel 2/4/8):
A13: GPU (VRAM, ГБ) | B13: FP16 | C13: INT4 | D13: Комментарий
A14: A100 80GB (Ampere, HBM 2.0 ТБ/с) | B14: =CEILING(B10/80,1) | C14: =CEILING(C10/80,1) | D14: FP16 → 3, берём 4 (TP=4); INT4 → 2 (TP=2, NVLink)
A15: T4 16GB (Turing, 300 ГБ/с) | B15: =CEILING(B10/16,1) | C15: =CEILING(C10/16,1) | D15: НЕПРИГОДНА: нет FlashAttention (Ampere+), нет BF16, слабые INT4-ядра, PCIe
A16: L4 24GB (Ada, 300 ГБ/с) | B16: =CEILING(B10/24,1) | C16: =CEILING(C10/24,1) | D16: по памяти INT4 = 4 карты, но bandwidth ×6.7 хуже A100; в RU-облаках почти нет

Sheet 3_Throughput
A1: Проверка по пропускной способности (компьют-потолок, эфф. утилизация ~50%)
A2: FLOPs на токен ≈ 2×N. Потолок ток/с = TFLOPS(эфф.) / (2×N). A100: 312 TFLOPS FP16 dense.
A4: Конфигурация реплики | B4: Потолок ток/с | C4: RPM на реплику | D4: Реплик на 1000 RPM
A5: FP16 · 4× A100 NVLink (TP=4) | B5: =4*312000/(2*'1_Параметры'!B5)*0.5 | C5: =B5/'1_Параметры'!B16*60 | D5: =CEILING(1000/C5,1)
A6: INT4 · 2× A100 NVLink (TP=2) | B6: =2*312000/(2*'1_Параметры'!B5)*0.5 | C6: =B6/'1_Параметры'!B16*60 | D6: =CEILING(1000/C6,1)
A7: INT4 · 4× T4 (PCIe) | B7: =4*65000/(2*'1_Параметры'!B5)*0.5 | C7: =B7/'1_Параметры'!B16*60 | D7: =CEILING(1000/C7,1)
A8: INT4 · 4× L4 (PCIe) | B8: =4*121000/(2*'1_Параметры'!B5)*0.5 | C8: =B8/'1_Параметры'!B16*60 | D8: =CEILING(1000/C8,1)
A10: Вывод: FP16 4×A100 держит ~1060 RPM (впритык, без запаса) → для прод-надёжности 2 реплики (8× A100). INT4 2×A100 держит ~530 RPM → 2 реплики (4× A100) с HA из коробки. T4: ~440 RPM на 4 карты формально, реально ниже (нет FA/AWQ-ядер) + латентность.

Sheet 4_Облака
A1: Шаг 2 · Стоимость аренды (публичные прайсы, зафиксировано 07.07.2026)
A2: Облако А: immers.cloud (https://immers.cloud/gpu/a100/) · Облако Б: Intelion Cloud (https://intelion.cloud/tesla-a100-80gb/, «от», скидки 3/6/12 мес = 8/15/25%)
A4: Конфигурация | B4: Облако | C4: ₽/час | D4: Реплик | E4: ₽/месяц | F4: Комментарий
A5: INT4 · 2× A100 NVLink · 1 реплика (~530 RPM) | B5: immers.cloud | C5: 439.97 | D5: 1 | E5: =C5*D5*'1_Параметры'!B23 | F5: порог половинной нагрузки
A6: INT4 · 2× A100 · 1 реплика | B6: Intelion («от») | C6: 346 | D6: 1 | E6: =C6*D6*'1_Параметры'!B23 | F6: 2×173 ₽/ч
A7: INT4 · 2 реплики 2× A100 = 4× A100 (1000 RPM) ★ | B7: immers.cloud | C7: 439.97 | D7: 2 | E7: =C7*D7*'1_Параметры'!B23 | F7: рекомендация: HA из коробки
A8: INT4 · 2 реплики 2× A100 ★ | B8: Intelion («от») | C8: 346 | D8: 2 | E8: =C8*D8*'1_Параметры'!B23 | F8: =505 160 ₽; с −25% (12 мес) = 378 870 ₽
A9: FP16 · 4× A100 · 1 реплика (~1060 RPM, впритык) | B9: immers.cloud | C9: 879.13 | D9: 1 | E9: =C9*D9*'1_Параметры'!B23 | F9: 44 vCPU/512 ГБ
A10: FP16 · 4× A100 · 1 реплика | B10: Intelion («от») | C10: 692 | D10: 1 | E10: =C10*D10*'1_Параметры'!B23 | F10: 4×173 ₽/ч
A11: FP16 · 8× A100 NVLink (прод-запас) | B11: immers.cloud | C11: 1677.58 | D11: 1 | E11: =C11*D11*'1_Параметры'!B23 | F11: 44 vCPU/704 ГБ
A12: FP16 · 2 реплики 4× A100 (прод-запас) | B12: Intelion («от») | C12: 692 | D12: 2 | E12: =C12*D12*'1_Параметры'!B23 | F12: с −25% (12 мес) = 757 740 ₽
A13: T4-флот · 5 реплик 4× T4 = 20× T4 (формально) | B13: immers.cloud | C13: 105.84 | D13: 5 | E13: =C13*D13*'1_Параметры'!B23 | F13: антипример: дешёвая карта ≠ дешёвый флот
A15: Справочно: Yandex Cloud (gpu-standard-v3, A100 80GB) и Cloud.ru публикуют цены только в JS-калькуляторах — для расчёта взяты два облака с открытым прайсом; методика идентична.

Sheet 5_Оптимизация
A1: Шаг 3 · Эффект батчинга / vLLM (сценарий INT4, реплика 2× A100, immers.cloud)
A3: Режим | B3: Реплик | C3: ₽/месяц | D3: Экономия vs без батчинга | E3: Комментарий
A4: Без батчинга (batch=1, последовательно) | B4: =CEILING('1_Параметры'!B13/(60/('2_Sizing_VRAM'!C6)),1) | C4: =B4*439.97*'1_Параметры'!B23 | D4: =1-C4/C$4 | E4: 8.3 запр/мин на реплику → ~121 реплика (242× A100)
A5: Статичный батчинг (naive) | B5: 4 | C5: =B5*439.97*'1_Параметры'!B23 | D5: =1-C5/C$4 | E5: ~50% эффективности continuous: простой на выравнивании длин
A6: vLLM: continuous batching + PagedAttention ★ | B6: 2 | C6: =B6*439.97*'1_Параметры'!B23 | D6: =1-C6/C$4 | E6: предел ~530 RPM/реплика; PagedAttention убирает до 90% потерь KV-VRAM
A8: Прогноз экономии: continuous batching (vLLM) снижает счёт с ~38.9 млн ₽/мес (без батчинга) до 642 тыс ₽/мес — экономия ~98%. Против статичного батчинга — ~2× (простои на выравнивании длин батча). Дополнительно: FP8/INT8-квантование KV-кэша удваивает ёмкость по одновременным запросам без новых карт.

Sheet 6_Вывод
A1: Шаг 4 · Рекомендация
A3: 1. Llama-3-70B INT4 (AWQ или GPTQ) под vLLM (continuous batching + PagedAttention + FlashAttention-2).
A4: 2. Конфигурация: 2 реплики × (2× A100 80GB NVLink) = 4× A100. Память: 83 ГБ/реплику из 160 доступных — большой KV-бюджет под длинные контексты. Throughput: 2×530 ≈ 1060 RPM с HA из коробки (отказ одной реплики = деградация до 530 RPM, а не даунтайм).
A5: 3. Стоимость: immers.cloud ~642 тыс ₽/мес; Intelion ~505 тыс ₽/мес («от»), при годовом резерве (−25%) ~379 тыс ₽/мес.
A6: 4. FP16 оправдан только если офлайн-eval (урок 13) покажет недопустимую деградацию INT4: тогда 8× A100 ≈ 1.0–1.2 млн ₽/мес (×2 дороже) — при том же качестве обслуживания.
A7: 5. T4 — непригодна (Turing: нет FlashAttention/BF16, 16 ГБ, PCIe): «дешёвая карта» оборачивается флотом 20+ карт с худшей латентностью за сопоставимые деньги. L4 по памяти проходит в INT4 (4×24 ГБ), но 300 ГБ/с bandwidth и фактическое отсутствие в RU-облаках снимают её с рассмотрения для 70B; её ниша — модели 7–8B.
A8: 6. Квантование INT4 снижает требование VRAM с 207 до 83 ГБ (−60%): вместо обязательных 4 карт в одном сервере — пары карт, т.е. более дешёвые и доступные конфигурации, плавное масштабирование шагом ~530 RPM и дешёвый DR-резерв.
